maxim_kuzin_hw2/FastHistogram.py
maxim_kuzin_hw2/__init__.py
maxim_kuzin_hw2-0.0.1.dist-info/METADATA
maxim_kuzin_hw2-0.0.1.dist-info/WHEEL
maxim_kuzin_hw2-0.0.1.dist-info/top_level.txt
maxim_kuzin_hw2-0.0.1.dist-info/RECORD
