Metadata-Version: 2.1
Name: maxim-kuzin-hw2
Version: 0.0.1
Summary: A example Python package
Home-page: https://github.com/shuds13/pyexample
Author: Maxim Kuzin
Author-email: 12345min@mail.ru
License: BSD 2-clause
Platform: UNKNOWN
Classifier: Development Status :: 1 - Planning
Classifier: Intended Audience :: Science/Research
Classifier: License :: OSI Approved :: BSD License
Classifier: Operating System :: POSIX :: Linux
Classifier: Programming Language :: Python :: 2
Classifier: Programming Language :: Python :: 2.7
Classifier: Programming Language :: Python :: 3
Classifier: Programming Language :: Python :: 3.4
Classifier: Programming Language :: Python :: 3.5
Requires-Dist: numpy
Requires-Dist: matplotlib
